CHANGELOG
LICENSE
MANIFEST.in
README.txt
setup.py
djig/__init__.py
djig/admin.py
djig/api.py
djig/models.py
djig/search_indexes.py
djig/sitemap.py
djig/tests.py
djig/text_utils.py
djig/urls.py
djig/views.py
djig.egg-info/PKG-INFO
djig.egg-info/SOURCES.txt
djig.egg-info/dependency_links.txt
djig.egg-info/not-zip-safe
djig.egg-info/top_level.txt
djig/management/__init__.py
djig/management/commands/__init__.py
djig/management/commands/__private.py
djig/management/commands/calculate_scores.py
djig/management/commands/fix_mysql.py
djig/templates/djig/detail.html
djig/templates/djig/index.html
djig/templates/djig/submit_link.html
djig/templates/search/indexes/djig/article_text.txt